iotccm_sdk/__init__.py
iotccm_sdk/version.py
iotccm_sdk/capability/__init__.py
iotccm_sdk/capability/actuator_capability.py
iotccm_sdk/capability/capability.py
iotccm_sdk/capability/processor_capability.py
iotccm_sdk/capability/sensor_capability.py
iotccm_sdk/capability/store_capability.py
iotccm_sdk/component/__init__.py
iotccm_sdk/component/component.py
iotccm_sdk-0.0.1a2.dist-info/LICENSE
iotccm_sdk-0.0.1a2.dist-info/METADATA
iotccm_sdk-0.0.1a2.dist-info/WHEEL
iotccm_sdk-0.0.1a2.dist-info/top_level.txt
iotccm_sdk-0.0.1a2.dist-info/RECORD
