Metadata-Version: 2.1
Name: iotccm-sdk
Version: 0.0.1a2
Summary: IoT CCM SDK for Python 3
Home-page: https://gitlab.com/prometheuscomputing/nist-ssd-iot-testbed/iot_ccm_sdk
Author: NIST Software and Systems Division
Author-email: omarilias.elmimouni@nist.gov
License: UNKNOWN
Project-URL: Bug Tracker, https://gitlab.com/prometheuscomputing/nist-ssd-iot-testbed/iot_ccm_sdk/-/issues
Project-URL: Documentation, https://gitlab.com/prometheuscomputing/nist-ssd-iot-testbed/iot_ccm_sdk/-/wikis/home
Platform: UNKNOWN
Classifier: Programming Language :: Python :: 3
Classifier: License :: OSI Approved :: MIT License
Classifier: Operating System :: OS Independent
Requires-Python: >=3.6
Requires-Dist: requests (<3.0,>=2.9.1)
Provides-Extra: dev
Requires-Dist: pytest ; extra == 'dev'
Requires-Dist: flake8 ; extra == 'dev'
Requires-Dist: coverage ; extra == 'dev'
Requires-Dist: pylint ; extra == 'dev'
Requires-Dist: setuptools ; extra == 'dev'
Requires-Dist: twine ; extra == 'dev'
